storageObject/__init__.py
storageObject/storageobject.py
storageobject-1.0.0.dist-info/licenses/LICENSE
storageobject-1.0.0.dist-info/METADATA
storageobject-1.0.0.dist-info/WHEEL
storageobject-1.0.0.dist-info/top_level.txt
storageobject-1.0.0.dist-info/RECORD
