Metadata-Version: 2.4
Name: storageobject
Version: 1.0.0
Summary: Ein thread-sicherer In-Memory Speicher, basierend auf Python-Dictionaries.
Author-email: Mogduz <deine.email@beispiel.de>
License: MIT License
Project-URL: Homepage, https://github.com/dein-github-benutzername/storageobject
Keywords: storage,thread-safe,in-memory,dictionary,cache
Classifier: Programming Language :: Python :: 3
Classifier: License :: OSI Approved :: MIT License
Classifier: Operating System :: OS Independent
Requires-Python: >=3.6
License-File: LICENSE
Dynamic: license-file
